{"is_source_file": false, "format": null, "description": null, "external_files": [], "external_methods": [], "published": [], "classes": [], "methods": [], "calls": [], "search-terms": ["App.css", "CSS variables", "theme management", "dark mode", "responsive design"], "state": 2, "file_id": 2, "knowledge_revision": 17, "git_revision": "f20d28dcd5bcd873356c3f64c9be0c39c49a0977", "hash": "22f9e17cc1848b56dbb244518ac2707e", "format-version": 4, "code-base-name": "counter_frontend", "filename": "counter_frontend/src/App.css", "revision_history": [{"17": "f20d28dcd5bcd873356c3f64c9be0c39c49a0977"}]}